geojson_tiles
