Metadata-Version: 1.0
Name: django-geojson-tiles
Version: 0.1.0
Summary: GeoJSON tile view for Django
Home-page: UNKNOWN
Author: Glen Robertson
Author-email: robertson.glen@gmail.com
License: UNKNOWN
Platform: UNKNOWN
